poetry_demo/__init__.py
poetry_demo/main.py
poetry_demo_farid_seifi-1.0.1.dist-info/METADATA
poetry_demo_farid_seifi-1.0.1.dist-info/WHEEL
poetry_demo_farid_seifi-1.0.1.dist-info/entry_points.txt
poetry_demo_farid_seifi-1.0.1.dist-info/RECORD
