Metadata-Version: 2.1
Name: poetry-demo-farid-seifi
Version: 1.0.1
Summary: 
Author: Farid Seifi
Author-email: faridsei@med.umich.edu
Requires-Python: >=3.10,<4.0
Classifier: Programming Language :: Python :: 3
Classifier: Programming Language :: Python :: 3.10
Classifier: Programming Language :: Python :: 3.11
Requires-Dist: pendulum (>=2.1,<3.0)
